{
    "Ar36": {
        "error": 0.00017598998175097802,
        "error_type": "SEM",
        "filter_outliers_dict": {
            "filter_outliers": true,
            "iterations": 1,
            "std_devs": 2
        },
        "fit": "Parabolic",
        "fn": 379,
        "include_baseline_error": false,
        "n": 400,
        "reviewed": true,
        "value": 0.0021909083926969315
    },
    "Ar37": {
        "error": 0.021981523842207074,
        "error_type": "SEM",
        "filter_outliers_dict": {
            "filter_outliers": true,
            "iterations": 1,
            "std_devs": 2
        },
        "fit": "Parabolic",
        "fn": 381,
        "include_baseline_error": false,
        "n": 400,
        "reviewed": true,
        "value": -0.2049732796207997
    },
    "Ar38": {
        "error": 0.004435740008145248,
        "error_type": "SEM",
        "filter_outliers_dict": {
            "filter_outliers": true,
            "iterations": 1,
            "std_devs": 2
        },
        "fit": "Linear",
        "fn": 377,
        "include_baseline_error": false,
        "n": 400,
        "reviewed": true,
        "value": -0.07958912524948189
    },
    "Ar39": {
        "error": 0.014519204059157772,
        "error_type": "SEM",
        "filter_outliers_dict": {
            "filter_outliers": true,
            "iterations": 1,
            "std_devs": 2
        },
        "fit": "Linear",
        "fn": 382,
        "include_baseline_error": false,
        "n": 400,
        "reviewed": true,
        "value": -0.05373892364139393
    },
    "Ar40": {
        "error": 0.019208976710575,
        "error_type": "SEM",
        "filter_outliers_dict": {
            "filter_outliers": true,
            "iterations": 1,
            "std_devs": 2
        },
        "fit": "Parabolic",
        "fn": 383,
        "include_baseline_error": false,
        "n": 400,
        "reviewed": true,
        "value": 0.2602323308260879
    }
}