{
    "Ar36": {
        "error": 0.00017557834882493003, 
        "error_type": "SEM", 
        "filter_outliers_dict": {
            "filter_outliers": true, 
            "iterations": 2, 
            "std_devs": 2
        }, 
        "fit": "Parabolic", 
        "value": 0.002026106760275268
    }, 
    "Ar37": {
        "error": 0.011833461738220424, 
        "error_type": "SEM", 
        "filter_outliers_dict": {
            "filter_outliers": true, 
            "iterations": 2, 
            "std_devs": 2
        }, 
        "fit": "linear", 
        "value": -0.380473897686909
    }, 
    "Ar38": {
        "error": 0.004438504783671448, 
        "error_type": "SEM", 
        "filter_outliers_dict": {
            "filter_outliers": true, 
            "iterations": 2, 
            "std_devs": 2
        }, 
        "fit": "linear", 
        "value": -0.07006303122959581
    }, 
    "Ar39": {
        "error": 0.02575862333419062, 
        "error_type": "SEM", 
        "filter_outliers_dict": {
            "filter_outliers": true, 
            "iterations": 2, 
            "std_devs": 2
        }, 
        "fit": "Parabolic", 
        "value": -0.01860776791147419
    }, 
    "Ar40": {
        "error": 0.020875990802497694, 
        "error_type": "SEM", 
        "filter_outliers_dict": {
            "filter_outliers": true, 
            "iterations": 2, 
            "std_devs": 2
        }, 
        "fit": "Parabolic", 
        "value": 0.24430242621448248
    }
}